{
  "telegram_api_data": {
    "chat": {
      "id": -1002645770363,
      "type": "supergroup",
      "title": "Akaere Internet Exchange Point | offtopic"
    },
    "date": 1766299484,
    "from": {
      "id": 8461935548,
      "is_bot": false,
      "username": "RuiFeng_12",
      "last_name": "Feng",
      "first_name": "Rui",
      "is_premium": true
    },
    "text": "\u6211sfz\u7b2c17\u4f4d\u662f\u5076\u6570\uff08\u4e0d\u662f",
    "message_id": 535162,
    "_db_info": {
      "id": 38381,
      "created_at": "2025-12-21T14:44:45.477064",
      "message_type": "text",
      "media_sha1s": []
    }
  },
  "extraction_metadata": {
    "extracted_at": "2025-12-21T06:48:21.261801Z",
    "extracted_by": "sign_command",
    "original_format": "telegram_api_v6.4"
  }
}